azula/__init__.py
azula/debug.py
azula/denoise.py
azula/hub.py
azula/noise.py
azula/sample.py
azula/guidance/__init__.py
azula/guidance/cfg.py
azula/guidance/diffpir.py
azula/guidance/dps.py
azula/guidance/jfps.py
azula/guidance/mmps.py
azula/guidance/pgdm.py
azula/guidance/repaint.py
azula/guidance/tds.py
azula/guidance/tmpd.py
azula/linalg/__init__.py
azula/linalg/covariance.py
azula/linalg/solve.py
azula/nn/__init__.py
azula/nn/attention.py
azula/nn/embedding.py
azula/nn/layers.py
azula/nn/unet.py
azula/nn/utils.py
azula/nn/vit.py
azula/plugins/__init__.py
azula/plugins/utils.py
azula/plugins/adm/__init__.py
azula/plugins/adm/cards.yml
azula/plugins/edm/__init__.py
azula/plugins/edm/cards.yml
azula/plugins/eldm/__init__.py
azula/plugins/eldm/cards.yml
azula/plugins/flux/__init__.py
azula/plugins/flux/cards.yml
azula/plugins/sana/__init__.py
azula/plugins/sana/cards.yml
azula/plugins/sd/__init__.py
azula/plugins/sd/cards.yml
azula/plugins/vdm/__init__.py
azula/plugins/vdm/cards.yml
azula-0.6.0.dist-info/licenses/LICENSE
azula-0.6.0.dist-info/METADATA
azula-0.6.0.dist-info/WHEEL
azula-0.6.0.dist-info/top_level.txt
azula-0.6.0.dist-info/RECORD
