Metadata-Version: 2.4
Name: azula
Version: 0.6.0
Summary: Diffusion models in PyTorch
Author-email: The Probabilists <theprobabilists@gmail.com>
License-Expression: MIT
Project-URL: documentation, https://azula.readthedocs.io
Project-URL: source, https://github.com/probabilists/azula
Project-URL: tracker, https://github.com/probabilists/azula/issues
Keywords: torch,diffusion models,probability,distribution,generative,deep learning
Classifier: Intended Audience :: Developers
Classifier: Intended Audience :: Science/Research
Classifier: Natural Language :: English
Classifier: Operating System :: OS Independent
Classifier: Programming Language :: Python :: 3
Requires-Python: >=3.9
License-File: LICENSE
Requires-Dist: einops>=0.7.0
Requires-Dist: gdown>=5.1.0
Requires-Dist: torch>=2.0.0
Requires-Dist: torchvision>=0.15.0
Provides-Extra: docs
Requires-Dist: docutils==0.19; extra == "docs"
Requires-Dist: furo==2024.5.6; extra == "docs"
Requires-Dist: myst-nb==1.0.0; extra == "docs"
Requires-Dist: sphinx==7.3.7; extra == "docs"
Provides-Extra: lint
Requires-Dist: pre-commit>=3.7.0; extra == "lint"
Requires-Dist: ruff==0.9.9; extra == "lint"
Provides-Extra: test
Requires-Dist: pytest>=8.0.0; extra == "test"
Dynamic: license-file
